setup.py
NaN_Rate_Calc_Vis/NaN_Rate_Calc_Vis.py
NaN_Rate_Calc_Vis/__init__.py
NaN_Rate_Calc_Vis.egg-info/PKG-INFO
NaN_Rate_Calc_Vis.egg-info/SOURCES.txt
NaN_Rate_Calc_Vis.egg-info/dependency_links.txt
NaN_Rate_Calc_Vis.egg-info/not-zip-safe
NaN_Rate_Calc_Vis.egg-info/top_level.txt