Metadata-Version: 2.1
Name: NaN-Rate-Calc-Vis
Version: 1.1
Summary: Calculate, analyze and visualize the NaN values in a given Dataframe
Home-page: https://github.com/maximkiesel1/Package_PyPi_NaN_Calc_Visual
Author: Maxim Kiesel
Author-email: maxim.kiese@yahoo.com
License: MIT
